ineq/__init__.py
ineq/curves.py
ineq/indexes.py
ineq/tables.py
ineq-0.1.dist-info/DESCRIPTION.rst
ineq-0.1.dist-info/METADATA
ineq-0.1.dist-info/RECORD
ineq-0.1.dist-info/WHEEL
ineq-0.1.dist-info/metadata.json
ineq-0.1.dist-info/top_level.txt
